interconnection/__init__.py
interconnection/common/__init__.py
interconnection/common/header_pb2.py
interconnection/handshake/__init__.py
interconnection/handshake/entry_pb2.py
interconnection/handshake/algos/__init__.py
interconnection/handshake/algos/lr_pb2.py
interconnection/handshake/algos/optimizer_pb2.py
interconnection/handshake/algos/psi_pb2.py
interconnection/handshake/algos/sgb_pb2.py
interconnection/handshake/op/__init__.py
interconnection/handshake/op/sigmoid_pb2.py
interconnection/handshake/protocol_family/__init__.py
interconnection/handshake/protocol_family/ecc_pb2.py
interconnection/handshake/protocol_family/phe_pb2.py
interconnection/handshake/protocol_family/ss_pb2.py
interconnection/runtime/__init__.py
interconnection/runtime/data_exchange_pb2.py
interconnection/runtime/ecdh_psi_pb2.py
interconnection/runtime/phe_pb2.py
interconnection-0.2.0.dev0.dist-info/LICENSE
interconnection-0.2.0.dev0.dist-info/METADATA
interconnection-0.2.0.dev0.dist-info/WHEEL
interconnection-0.2.0.dev0.dist-info/top_level.txt
interconnection-0.2.0.dev0.dist-info/RECORD
