Metadata-Version: 2.1
Name: interconnection
Version: 0.2.0.dev0
Summary: Interconnection aims to define standard interconnection protocols for multi-layers in privacy-preserving computing.
Home-page: https://github.com/secretflow/interconnection
Author: SecretFlow Team
Author-email: secretflow-contact@service.alipay.com
License: Apache 2.0
Classifier: Programming Language :: Python :: 3
License-File: LICENSE
Requires-Dist: protobuf <5,>=4
